<?xml version="1.0" encoding="utf-8"?>
<!DOCTYPE hibernate-mapping PUBLIC "-//Hibernate/Hibernate Mapping DTD 3.0//EN"
"http://hibernate.sourceforge.net/hibernate-mapping-3.0.dtd">
<!-- 
    Mapping file autogenerated by MyEclipse Persistence Tools
-->
<hibernate-mapping>
    <class name="com.secret.pojo.OrderAddressPojo" table="order_address" catalog="asossh">
        <id name="orderAddressId" type="java.lang.Integer">
            <column name="order_address_id" />
            <generator class="identity" />
        </id>
        <property name="orderName" type="java.lang.String">
            <column name="order_name" length="64" not-null="true" />
        </property>
        <property name="province" type="java.lang.String">
            <column name="province" length="128" not-null="true" />
        </property>
        <property name="city" type="java.lang.String">
            <column name="city" length="128" />
        </property>
        <property name="county" type="java.lang.String">
            <column name="county" length="128" />
        </property>
        <property name="otherAddress" type="java.lang.String">
            <column name="other_address" length="128" not-null="true" />
        </property>
        <property name="postCode" type="java.lang.Integer">
            <column name="postCode" />
        </property>
        <property name="cellphone" type="java.lang.String">
            <column name="cellphone" length="64" />
        </property>
        <property name="phonesection" type="java.lang.String">
            <column name="phonesection" length="16" />
        </property>
        <property name="phonecode" type="java.lang.String">
            <column name="phonecode" length="64" />
        </property>
        <property name="otherphone" type="java.lang.String">
            <column name="otherphone" length="64" />
        </property>
       <!--  <property name="userId" type="java.lang.Integer">
            <column name="user_id" not-null="true" />
        </property> -->
        <property name="orderAddressStatus" type="java.lang.String">
            <column name="order_address_status" length="1" not-null="true" />
        </property>
        <many-to-one name="userPojo"  lazy="false" fetch="join"
  		cascade="save-update" class="com.secret.pojo.UserPojo" column="user_id"
  		></many-to-one>
    </class>
</hibernate-mapping>
